thot_core/__init__.py
thot_core/runner.py
thot_core/classes/__init__.py
thot_core/classes/asset.py
thot_core/classes/base_object.py
thot_core/classes/container.py
thot_core/classes/metadata.py
thot_core/classes/note.py
thot_core/classes/resource.py
thot_core/classes/role.py
thot_core/classes/script.py
thot_core/classes/thot_interface.py
thot_core/db/__init__.py
thot_core/db/collection_interface.py
thot_core/drivers/__init__.py
thot_core/drivers/driver_interface.py
thot_core/drivers/drivers.py
thot_core/runners/__init__.py
thot_core/runners/common.py
thot_core/runners/runner_async.py
thot_core/runners/runner_async36.py
thot_core/runners/runner_multithread.py
thot_core-0.4.10.dist-info/LICENSE
thot_core-0.4.10.dist-info/METADATA
thot_core-0.4.10.dist-info/WHEEL
thot_core-0.4.10.dist-info/entry_points.txt
thot_core-0.4.10.dist-info/top_level.txt
thot_core-0.4.10.dist-info/RECORD
